{
  "ACTIVISM Accepts Bitcoin": "Yes",
  "ACTIVISM Anonymous Payment Method": "Email",
  "ACTIVISM Meets PrivacyTools IO Criteria": "No",
  "AFFILIATES Give Full Disclosure": "",
  "AFFILIATES Practice Ethical Copy": "",
  "AVAILABILITY # of Connections": "1",
  "AVAILABILITY # of Countries": "",
  "AVAILABILITY # of Servers": "",
  "ETHICS Contradictory Logging Policies": "",
  "ETHICS Falsely Claims 100% Effective": "",
  "ETHICS Incentivizes Social Media Spam": "",
  "JURISDICTION Based In (Country)": "Taiwan",
  "JURISDICTION Fourteen Eyes?": "No",
  "JURISDICTION Freedom Status": "Free",
  "LEAK PROTECTION 1st Party DNS Servers": "No",
  "LEAK PROTECTION IPv6 Supported / Blocked": "No",
  "LEAK PROTECTION Kill Switch": "No",
  "LOGGING Logs Bandwidth": "",
  "LOGGING Logs DNS Requests": "",
  "LOGGING Logs IP Address": "Yes",
  "LOGGING Logs Timestamps": "Yes",
  "LOGGING Logs Traffic": "Yes",
  "POLICIES Forbids Spam": "",
  "POLICIES Requires Ethical Copy": "",
  "POLICIES Requires Full Disclosure": "",
  "PORT BLOCKING Auth SMTP": "",
  "PORT BLOCKING P2P": "Some",
  "PRICING $ / Connection / Month": "",
  "PRICING $ / Month (Annual Pricing)": "",
  "PRICING Free Trial": "No",
  "PRICING Refund Period (Days)": "0",
  "PROTOCOLS Offers OpenVPN": "No",
  "SECURITY Strongest Data Encryption": "",
  "SECURITY Strongest Handshake Encryption": "",
  "SECURITY Weakest Data Encryption": "",
  "SECURITY Weakest Handshake Encryption": "",
  "VPN SERVICE": "Seed4me",
  "WEBSITE # of External Trackers": "2",
  "WEBSITE # of Persistent Cookies": "3",
  "WEBSITE # of Proprietary APIs": "11",
  "WEBSITE SSL Cert issued to": "Self",
  "WEBSITE Server SSL Rating": "B"
}
